{
	"cmake" : 
	{
		"generator" : 
		{
			"multiConfig" : false,
			"name" : "Ninja"
		},
		"paths" : 
		{
			"cmake" : "C:/Users/Lenovo/AppData/Local/Android/Sdk/cmake/3.31.6/bin/cmake.exe",
			"cpack" : "C:/Users/Lenovo/AppData/Local/Android/Sdk/cmake/3.31.6/bin/cpack.exe",
			"ctest" : "C:/Users/Lenovo/AppData/Local/Android/Sdk/cmake/3.31.6/bin/ctest.exe",
			"root" : "C:/Users/Lenovo/AppData/Local/Android/Sdk/cmake/3.31.6/share/cmake-3.31"
		},
		"version" : 
		{
			"isDirty" : false,
			"major" : 3,
			"minor" : 31,
			"patch" : 6,
			"string" : "3.31.6",
			"suffix" : ""
		}
	},
	"objects" : 
	[
		{
			"jsonFile" : "codemodel-v2-0f232471fdf4f033657f.json",
			"kind" : "codemodel",
			"version" : 
			{
				"major" : 2,
				"minor" : 7
			}
		},
		{
			"jsonFile" : "cache-v2-e9e48d93ad982de787a7.json",
			"kind" : "cache",
			"version" : 
			{
				"major" : 2,
				"minor" : 0
			}
		},
		{
			"jsonFile" : "cmakeFiles-v1-32c540aad95827cfdf4c.json",
			"kind" : "cmakeFiles",
			"version" : 
			{
				"major" : 1,
				"minor" : 1
			}
		}
	],
	"reply" : 
	{
		"client-agp" : 
		{
			"cache-v2" : 
			{
				"jsonFile" : "cache-v2-e9e48d93ad982de787a7.json",
				"kind" : "cache",
				"version" : 
				{
					"major" : 2,
					"minor" : 0
				}
			},
			"cmakeFiles-v1" : 
			{
				"jsonFile" : "cmakeFiles-v1-32c540aad95827cfdf4c.json",
				"kind" : "cmakeFiles",
				"version" : 
				{
					"major" : 1,
					"minor" : 1
				}
			},
			"codemodel-v2" : 
			{
				"jsonFile" : "codemodel-v2-0f232471fdf4f033657f.json",
				"kind" : "codemodel",
				"version" : 
				{
					"major" : 2,
					"minor" : 7
				}
			}
		}
	}
}
